{
 "b3_W8": {
  "flags": {
   "insufficient_history": false
  },
  "indicators": {
   "b_401": 0,
   "b_402": 0,
   "b_8kfreq": 0,
   "b_ka": 1,
   "b_nt": 0,
   "b_qa": 1
  },
  "score": 2
 },
 "b4": {
  "cite": "D61 — 커버 2/13, 상태를 생략하지 않고 기록",
  "flags": {
   "insufficient_history": false,
   "no_shares_denominator": false,
   "no_si_file": true,
   "revision_seen_diagnostic": 0,
   "slope_unavailable": false
  },
  "state": "not_computable"
 },
 "base_case_id": "case_01",
 "base_cutoff": "2016-02-28",
 "cik": "0001158172",
 "documents": [
  {
   "accession": "0000950123-11-075023",
   "filed": "2011-08-09",
   "form": "10-Q",
   "n_facts": 12
  },
  {
   "accession": "0001193125-11-295409",
   "filed": "2011-11-03",
   "form": "10-Q",
   "n_facts": 12
  },
  {
   "accession": "0001193125-12-072772",
   "filed": "2012-02-22",
   "form": "10-K",
   "n_facts": 51
  },
  {
   "accession": "0001193125-12-207751",
   "filed": "2012-05-03",
   "form": "10-Q",
   "n_facts": 19
  },
  {
   "accession": "0001193125-12-332128",
   "filed": "2012-08-02",
   "form": "10-Q",
   "n_facts": 15
  },
  {
   "accession": "0001158172-12-000049",
   "filed": "2012-11-02",
   "form": "10-Q",
   "n_facts": 15
  },
  {
   "accession": "0001158172-13-000004",
   "filed": "2013-02-20",
   "form": "10-K",
   "n_facts": 51
  },
  {
   "accession": "0001158172-13-000034",
   "filed": "2013-05-13",
   "form": "10-Q/A",
   "n_facts": 20
  },
  {
   "accession": "0001158172-13-000050",
   "filed": "2013-07-30",
   "form": "10-Q",
   "n_facts": 15
  },
  {
   "accession": "0001158172-13-000060",
   "filed": "2013-10-29",
   "form": "10-Q",
   "n_facts": 15
  },
  {
   "accession": "0001158172-14-000004",
   "filed": "2014-02-18",
   "form": "10-K",
   "n_facts": 84
  },
  {
   "accession": "0001158172-14-000020",
   "filed": "2014-05-01",
   "form": "10-Q",
   "n_facts": 40
  },
  {
   "accession": "0001158172-14-000048",
   "filed": "2014-08-05",
   "form": "10-Q",
   "n_facts": 30
  },
  {
   "accession": "0001158172-14-000054",
   "filed": "2014-10-29",
   "form": "10-Q",
   "n_facts": 46
  }
 ],
 "generator": "e2gen-v1 (EARLINESS_PLAN §1–§2 + D65)",
 "group": "treatment",
 "guard": {
  "documents_passed": 565
 },
 "j": 5,
 "payload_sha256": "c79239b1cd34a2e78ccec036cac3fcebdbc190cdd0d35fb244efa7a4dce3709f",
 "snapshot_cutoff": "2014-10-30",
 "snapshot_id": "case_01_s5",
 "ticker": "SCOR",
 "tier": "wave1"
}
