{"cik":1410738,"taxonomy":"dei","tag":"EntityPublicFloat","label":"Entity Public Float","description":"The aggregate market value of the voting and non-voting common equity held by non-affiliates computed by reference to the price at which the common equity was last sold, or the average bid and asked price of such common equity, as of the last business day of the registrant's most recently completed second fiscal quarter.","entityName":"VoIP-PAL.COM INC.","units":{"USD":[{"end":"2016-03-31","val":46435694,"accn":"0001580695-17-000021","fy":2016,"fp":"FY","form":"10-K","filed":"2017-01-11","frame":"CY2016Q1I"},{"end":"2017-03-31","val":41185448,"accn":"0001580695-18-000029","fy":2017,"fp":"FY","form":"10-K","filed":"2018-01-12","frame":"CY2017Q1I"},{"end":"2018-03-31","val":95744566,"accn":"0001580695-19-000017","fy":2018,"fp":"FY","form":"10-K","filed":"2019-01-11","frame":"CY2018Q1I"},{"end":"2019-03-31","val":23999691,"accn":"0001580695-20-000032","fy":2019,"fp":"FY","form":"10-K","filed":"2020-01-13","frame":"CY2019Q1I"},{"end":"2020-03-31","val":14621863,"accn":"0001493152-20-023764","fy":2020,"fp":"FY","form":"10-K","filed":"2020-12-16"},{"end":"2020-03-31","val":14621863,"accn":"0001493152-22-036629","fy":2022,"fp":"FY","form":"10-K","filed":"2022-12-28","frame":"CY2020Q1I"},{"end":"2021-03-31","val":24270170,"accn":"0001493152-21-031576","fy":2021,"fp":"FY","form":"10-K","filed":"2021-12-15","frame":"CY2021Q1I"},{"end":"2023-03-31","val":101208134,"accn":"0001493152-23-045839","fy":2023,"fp":"FY","form":"10-K","filed":"2023-12-22"},{"end":"2023-03-31","val":101208134,"accn":"0001493152-24-006235","fy":2023,"fp":"FY","form":"10-K/A","filed":"2024-02-14"},{"end":"2023-03-31","val":101208134,"accn":"0001493152-24-052072","fy":2024,"fp":"FY","form":"10-K","filed":"2024-12-26"},{"end":"2023-03-31","val":101208134,"accn":"0001493152-25-029094","fy":2025,"fp":"FY","form":"10-K","filed":"2025-12-23","frame":"CY2023Q1I"}]}}